triangle_drawer/__init__.py
triangle_drawer/triangle.py
triangle_drawer-1.0.1.dist-info/LICENSE
triangle_drawer-1.0.1.dist-info/WHEEL
triangle_drawer-1.0.1.dist-info/METADATA
triangle_drawer-1.0.1.dist-info/RECORD
