Metadata-Version: 2.1
Name: triangle_drawer
Version: 1.0.1
Summary: A package to draw any triangle on screen.
Author-email: Deividas Tamkus <dtamkus@gmail.com>
Classifier: License :: OSI Approved :: MIT License
Requires-Dist: matplotlib >= 3.5.2, < 4
Project-URL: Home, https://github.com/deitam/TriangleDrawer
